RunDB_client-0.5.dist-info/DESCRIPTION.rst
RunDB_client-0.5.dist-info/METADATA
RunDB_client-0.5.dist-info/RECORD
RunDB_client-0.5.dist-info/WHEEL
RunDB_client-0.5.dist-info/metadata.json
RunDB_client-0.5.dist-info/top_level.txt
rundb/__init__.py
rundb/client/__init__.py
rundb/client/http_api_auth.py
rundb/client/rundbc.py
