Metadata-Version: 2.0
Name: RunDB-client
Version: 0.5
Summary: Client API for RunDB
Home-page: https://git.kern.phys.au.dk/ausa/RunDBC
Author: Michael Munch & Jesper Halkjær
Author-email: mm@phys.au.dk
License: MIT
Platform: UNKNOWN
Requires-Dist: requests (>2)
